logging_ext/__init__.py
logging_ext-1.0.2.dist-info/LICENSE.txt
logging_ext-1.0.2.dist-info/METADATA
logging_ext-1.0.2.dist-info/WHEEL
logging_ext-1.0.2.dist-info/top_level.txt
logging_ext-1.0.2.dist-info/RECORD
