Metadata-Version: 2.1
Name: logging-ext
Version: 1.0.2
Summary: logging extension;
Home-page: https://github.com/cykerway/logging-ext
Author: Cyker Way
Author-email: cykerway@example.com
License: UNKNOWN
Project-URL: Funding, https://paypal.me/cykerway
Project-URL: Source, https://github.com/cykerway/logging-ext/
Project-URL: Tracker, https://github.com/cykerway/logging-ext/issues
Keywords: logging,extension
Platform: UNKNOWN
Classifier: Development Status :: 4 - Beta
Classifier: Intended Audience :: Developers
Classifier: License :: OSI Approved :: GNU General Public License v3 (GPLv3)
Classifier: Programming Language :: Python :: 3.10
Classifier: Programming Language :: Python :: 3.6
Classifier: Programming Language :: Python :: 3.7
Classifier: Programming Language :: Python :: 3.8
Classifier: Programming Language :: Python :: 3.9
Classifier: Topic :: Software Development
